lifeguard_peewee/__init__.py
lifeguard_peewee/context.py
lifeguard_peewee/models.py
lifeguard_peewee/repositories.py
lifeguard_peewee/settings.py
lifeguard_peewee-0.0.2.dist-info/METADATA
lifeguard_peewee-0.0.2.dist-info/WHEEL
lifeguard_peewee-0.0.2.dist-info/top_level.txt
lifeguard_peewee-0.0.2.dist-info/RECORD
