Metadata-Version: 2.1
Name: lifeguard-peewee
Version: 0.0.2
Summary: Lifeguard integration with SQL servers using peewee
Home-page: https://github.com/LifeguardSystem/lifeguard-peewee
Author: Diego Rubin
Author-email: contact@diegorubin.dev
License: GPL2
Classifier: Development Status :: 3 - Alpha
Requires-Dist: lifeguard
Requires-Dist: peewee
